slurmray/RayLauncher.py
slurmray/__init__.py
slurmray/__main__.py
slurmray/assets/cleanup_old_projects.py
slurmray/assets/sbatch_template.sh
slurmray/assets/slurmray_server.sh
slurmray/assets/slurmray_server_template.py
slurmray/assets/spython_template.py
slurmray/backend/__init__.py
slurmray/backend/base.py
slurmray/backend/desi.py
slurmray/backend/local.py
slurmray/backend/remote.py
slurmray/backend/slurm.py
slurmray/cli.py
slurmray/detection.py
slurmray/file_sync.py
slurmray/scanner.py
slurmray/utils.py
slurmray-6.1.0.dist-info/LICENSE
slurmray-6.1.0.dist-info/METADATA
slurmray-6.1.0.dist-info/WHEEL
slurmray-6.1.0.dist-info/entry_points.txt
slurmray-6.1.0.dist-info/RECORD
