Metadata-Version: 2.3
Name: slurmray
Version: 6.1.0
Summary: SlurmRay is an official tool from DESI @ HEC UNIL for effortlessly distributing tasks on Slurm clusters (e.g., Curnagl) or standalone servers (e.g., ISIPOL09/Desi) using the Ray library.
License: Apache License
Keywords: ray,slurm,distributed-computing,hpc,desi,hec-unil
Author: Henri Jamet
Author-email: henri.jamet@unil.ch
Requires-Python: >=3.10,<3.13
Classifier: License :: Other/Proprietary License
Classifier: Programming Language :: Python :: 3
Classifier: Programming Language :: Python :: 3.10
Classifier: Programming Language :: Python :: 3.11
Classifier: Programming Language :: Python :: 3.12
Requires-Dist: dill (>=0.3.7,<0.4.0)
Requires-Dist: inquirer (>=3.1.3,<4.0.0)
Requires-Dist: paramiko (>=3.3.1,<4.0.0)
Requires-Dist: pdoc3 (>=0.10.0,<0.11.0)
Requires-Dist: python-dotenv (>=1.0.0,<2.0.0)
Requires-Dist: ray[data,serve,train,tune] (>=2.7.1,<3.0.0)
Requires-Dist: rich (>=14.2.0,<15.0.0)
Requires-Dist: setuptools (>=80.9.0,<81.0.0)
Requires-Dist: torch (>=2.9.1,<3.0.0)
Project-URL: Documentation, https://henri-jamet.vercel.app/cards/documentation/slurm-ray/slurm-ray/
Project-URL: Homepage, https://henri-jamet.vercel.app/
